kgraphagent/__init__.py
kgraphagent/kgraphagent_manager.py
kgraphagent/query/__init__.py
kgraphagent/query/kgraphagent_query.py
kgraphagent/utils/__init__.py
kgraphutils/__init__.py
kgraphutils/kgraph_utils.py
vitalsignsutils/__init__.py
vitalsignsutils/vitalsignsutils.py
kgraphagent-0.0.4.dist-info/LICENSE
kgraphagent-0.0.4.dist-info/METADATA
kgraphagent-0.0.4.dist-info/WHEEL
kgraphagent-0.0.4.dist-info/top_level.txt
kgraphagent-0.0.4.dist-info/RECORD
