Metadata-Version: 2.1
Name: kgraphagent
Version: 0.0.4
Summary: KGraph Agent
Home-page: https://github.com/vital-ai/kgraphagent
Author: Marc Hadfield
Author-email: marc@vital.ai
License: Apache License 2.0
Classifier: Programming Language :: Python :: 3.10
Classifier: License :: OSI Approved :: Apache Software License
Classifier: Operating System :: OS Independent
Requires-Python: >=3.10
License-File: LICENSE
Requires-Dist: requests >=2.31.0
Requires-Dist: vital-ai-vitalsigns >=0.1.21
Requires-Dist: vital-ai-domain >=0.1.7
Requires-Dist: six
Requires-Dist: pyyaml
Requires-Dist: vital-ai-haley-kg >=0.1.14
Requires-Dist: vital-agent-kg-utils >=0.1.1
Requires-Dist: kgraphmemory >=0.0.5
Requires-Dist: kgraphservice >=0.0.5
Requires-Dist: kgraphgen >=0.0.1
Requires-Dist: rdflib ==7.0.0
Requires-Dist: SPARQLWrapper ==2.0.0
